mindswarm/__init__.py
mindswarm-0.0.1.dist-info/METADATA
mindswarm-0.0.1.dist-info/WHEEL
mindswarm-0.0.1.dist-info/RECORD
