Metadata-Version: 2.3
Name: mindswarm
Version: 0.0.1
Summary: Collective AI orchestration framework.
License: MIT
Keywords: ai,agents,orchestration,multi-agent,swarm,collective intelligence
Author: Tyson Chan
Author-email: tyson.chan@proton.me
Requires-Python: >=3.9,<4.0
Classifier: License :: OSI Approved :: MIT License
Classifier: Programming Language :: Python :: 3
Classifier: Programming Language :: Python :: 3.9
Classifier: Programming Language :: Python :: 3.10
Classifier: Programming Language :: Python :: 3.11
Classifier: Programming Language :: Python :: 3.12
Classifier: Programming Language :: Python :: 3.13
